[
  {
    "at": "2026-06-13T14:33:50.009Z",
    "price_idr": 29846352
  },
  {
    "at": "2026-06-13T19:30:42.667Z",
    "price_idr": 29794835
  },
  {
    "at": "2026-06-14T05:21:07.777Z",
    "price_idr": 29804502
  },
  {
    "at": "2026-06-14T10:23:14.195Z",
    "price_idr": 29796131
  },
  {
    "at": "2026-06-14T14:43:40.444Z",
    "price_idr": 29438002
  },
  {
    "at": "2026-06-14T20:54:58.598Z",
    "price_idr": 29707498
  },
  {
    "at": "2026-06-15T05:33:13.965Z",
    "price_idr": 30366155
  },
  {
    "at": "2026-06-15T12:56:56.266Z",
    "price_idr": 31431820
  },
  {
    "at": "2026-06-15T18:28:03.051Z",
    "price_idr": 32395348
  },
  {
    "at": "2026-06-15T22:50:40.487Z",
    "price_idr": 31708030
  }
]